polly/__init__.py
polly/cli.py
polly/client.py
polly/core.py
polly/server.py
python_polly-0.1.0.dist-info/LICENSE
python_polly-0.1.0.dist-info/METADATA
python_polly-0.1.0.dist-info/WHEEL
python_polly-0.1.0.dist-info/entry_points.txt
python_polly-0.1.0.dist-info/top_level.txt
python_polly-0.1.0.dist-info/RECORD
