Metadata-Version: 2.1
Name: python-polly
Version: 0.1.0
Summary: Wrapper for AWS Polly with segmentation, playback queue and client-server setup
Home-page: https://github.com/krisfris/python-polly
Author: Kris
Author-email: 31852063+krisfris@users.noreply.github.com
License: UNKNOWN
Platform: UNKNOWN
Requires-Dist: requests
Requires-Dist: click
Provides-Extra: server
Requires-Dist: appdirs ; extra == 'server'
Requires-Dist: pyaudio ; extra == 'server'
Requires-Dist: nltk ; extra == 'server'
Requires-Dist: boto3 ; extra == 'server'
Requires-Dist: werkzeug ; extra == 'server'
Requires-Dist: json-rpc ; extra == 'server'
Requires-Dist: pyqt5 ; extra == 'server'
